{
  "openapi": "3.1.0",
  "info": {
    "title": "MIDAS API",
    "description": "BackEnd API MIDAS",
    "version": "1.0.0"
  },
  "servers": [
    {
      "url": "http://localhost:8080",
      "description": "API para teste e desenvolvimento"
    }
  ],
  "paths":{
    "/auth/login": {
      "post": {
        "summary": "Login de usuário",
        "description": "Realiza o login de um usuário no sistema",
        "tags": ["Auth"],
        "requestBody": {
          "required": true,
          "content": {
            "application/json": {
              "schema": {
                "type": "object",
                "properties": {
                  "email": { "type": "string" },
                  "password": { "type": "string" }
                },
                "required": ["email", "password"]
              }
            }
          }
        },
        "responses": {
          "200": {
            "description": "OK",
            "content": {
              "application/json": {
                "schema": {
                  "type": "object",
                  "properties": {
                    "token": { "type": "string" },
                    "user_id": { "type": "string" },
                    "user_email": { "type": "string" }
                  }
                }
              }
            }
          },
          "400": {
            "description": "Bad Request",
            "content": {
              "application/json": {
                "schema": {
                  "type": "object",
                  "properties": {
                    "error": { "type": "string" }
                  }
                }
              }
            }
          },
          "404": {
            "description": "Not Found",
            "content": {
              "application/json": {
                "schema": {
                  "type": "object",
                  "properties": {
                    "error": { "type": "string" }
                  }
                }
              }
            }
          },
          "500": {
            "description": "Internal Server Error",
            "content": {
              "application/json": {
                "schema": {
                  "type": "object",
                  "properties": {
                    "error": { "type": "string" }
                  }
                }
              }
            }
          }
        }
      }
    },
    "/commodity": {
      "post": {
        "summary": "Criar uma nova commodity",
        "description": "Cria uma nova commodity no sistema",
        "tags": ["Commodity"],
        "security": [{ "bearerAuth": [] }],
        "requestBody": {
          "required": true,
          "content": {
            "application/json": {
              "schema": {
                "type": "object",
                "properties": {
                  "name": { "type": "string" },
                  "code": { "type": "string" },
                  "user_id": { "type": "string" }
                },
                "required": ["name", "code", "user_id"]
              }
            }
          }
        },
        "responses": {
          "201": {
            "description": "Created",
            "content": {
              "application/json": {
                "schema": {
                  "type": "object",
                  "properties": {
                    "id": { "type": "string" },
                    "name": { "type": "string" },
                    "code": { "type": "string" },
                    "user_id": { "type": "string" }
                  }
                }
              }
            }
          },
          "400": {
            "description": "Bad Request",
            "content": {
              "application/json": {
                "schema": {
                  "type": "object",
                  "properties": {
                    "error": { "type": "string" }
                  }
                }
              }
            }
          },
          "401": {
            "description": "Unauthorized"
          },
          "404": {
            "description": "Not Found",
            "content": {
              "application/json": {
                "schema": {
                  "type": "object",
                  "properties": {
                    "error": { "type": "string" }
                  }
                }
              }
            }
          },
          "406": {
            "description": "Not Acceptable",
            "content": {
              "application/json": {
                "schema": {
                  "type": "object",
                  "properties": {
                    "error": { "type": "string" }
                  }
                }
              }
            }
          },
          "409": {
            "description": "Conflict",
            "content": {
              "application/json": {
                "schema": {
                  "type": "object",
                  "properties": {
                    "error": { "type": "string" }
                  }
                }
              }
            }
          },
          "500": {
            "description": "Internal Server Error",
            "content": {
              "application/json": {
                "schema": {
                  "type": "object",
                  "properties": {
                    "error": { "type": "string" }
                  }
                }
              }
            }
          }
        }
      },
      "get": {
        "summary": "Obter commodities do usuário",
        "description": "Retorna a lista de commodities de um usuário",
        "tags": ["Commodity"],
        "security": [{ "bearerAuth": [] }],
        "parameters": [
          {
            "name": "userId",
            "in": "query",
            "required": true,
            "schema": {
              "type": "string"
            },
            "description": "ID do usuário"
          }
        ],
        "responses": {
          "200": {
            "description": "OK",
            "content": {
              "application/json": {
                "schema": {
                  "type": "object",
                  "properties": {
                    "commodities": {
                      "type": "array",
                      "items": {
                        "type": "object",
                        "properties": {
                          "id": { "type": "string" },
                          "name": { "type": "string" },
                          "code": { "type": "string" }
                        }
                      }
                    }
                  }
                }
              }
            }
          },
          "400": {
            "description": "Bad Request",
            "content": {
              "application/json": {
                "schema": {
                  "type": "object",
                  "properties": {
                    "error": { "type": "string" }
                  }
                }
              }
            }
          },
          "401": {
            "description": "Unauthorized"
          },
          "404": {
            "description": "Not Found",
            "content": {
              "application/json": {
                "schema": {
                  "type": "object",
                  "properties": {
                    "error": { "type": "string" }
                  }
                }
              }
            }
          },
          "406": {
            "description": "Not Acceptable",
            "content": {
              "application/json": {
                "schema": {
                  "type": "object",
                  "properties": {
                    "error": { "type": "string" }
                  }
                }
              }
            }
          },
          "500": {
            "description": "Internal Server Error",
            "content": {
              "application/json": {
                "schema": {
                  "type": "object",
                  "properties": {
                    "error": { "type": "string" }
                  }
                }
              }
            }
          }
        }
      }
    },
    "/commodity/{id}": {
      "put": {
        "summary": "Atualizar uma commodity",
        "description": "Atualiza uma commodity existente no sistema com base em seu ID",
        "tags": ["Commodity"],
        "security": [{ "bearerAuth": [] }],
        "parameters": [
          {
            "name": "id",
            "in": "path",
            "required": true,
            "schema": {
              "type": "string"
            },
            "description": "ID da commodity"
          }
        ],
        "requestBody": {
          "required": true,
          "content": {
            "application/json": {
              "schema": {
                "type": "object",
                "properties": {
                  "name": { "type": "string" },
                  "code": { "type": "string" }
                },
                "required": ["name", "code"]
              }
            }
          }
        },
        "responses": {
          "200": {
            "description": "OK",
            "content": {
              "application/json": {
                "schema": {
                  "type": "object",
                  "properties": {
                    "id": { "type": "string" },
                    "name": { "type": "string" },
                    "code": { "type": "string" }
                  }
                }
              }
            }
          },
          "400": {
            "description": "Bad Request",
            "content": {
              "application/json": {
                "schema": {
                  "type": "object",
                  "properties": {
                    "error": { "type": "string" }
                  }
                }
              }
            }
          },
          "401": {
            "description": "Unauthorized"
          },
          "404": {
            "description": "Not Found",
            "content": {
              "application/json": {
                "schema": {
                  "type": "object",
                  "properties": {
                    "error": { "type": "string" }
                  }
                }
              }
            }
          },
          "406": {
            "description": "Not Acceptable",
            "content": {
              "application/json": {
                "schema": {
                  "type": "object",
                  "properties": {
                    "error": { "type": "string" }
                  }
                }
              }
            }
          },
          "409": {
            "description": "Conflict",
            "content": {
              "application/json": {
                "schema": {
                  "type": "object",
                  "properties": {
                    "error": { "type": "string" }
                  }
                }
              }
            }
          },
          "500": {
            "description": "Internal Server Error",
            "content": {
              "application/json": {
                "schema": {
                  "type": "object",
                  "properties": {
                    "error": { "type": "string" }
                  }
                }
              }
            }
          }
        }
      },
      "delete": {
        "summary": "Deletar uma commodity",
        "description": "Deleta uma commodity existente no sistema com base em seu ID",
        "tags": ["Commodity"],
        "security": [{ "bearerAuth": [] }],
        "parameters": [
          {
            "name": "id",
            "in": "path",
            "required": true,
            "schema": {
              "type": "string"
            },
            "description": "ID da commodity"
          }
        ],
        "responses": {
          "204": {
            "description": "No Content"
          },
          "401": {
            "description": "Unauthorized"
          },
          "404": {
            "description": "Not Found",
            "content": {
              "application/json": {
                "schema": {
                  "type": "object",
                  "properties": {
                    "error": { "type": "string" }
                  }
                }
              }
            }
          },
          "406": {
            "description": "Not Acceptable",
            "content": {
              "application/json": {
                "schema": {
                  "type": "object",
                  "properties": {
                    "error": { "type": "string" }
                  }
                }
              }
            }
          },
          "500": {
            "description": "Internal Server Error",
            "content": {
              "application/json": {
                "schema": {
                  "type": "object",
                  "properties": {
                    "error": { "type": "string" }
                  }
                }
              }
            }
          }
        }
      }
    },
    "/site": {
      "post": {
        "summary": "Criar um novo site",
        "description": "Cria um novo site no sistema",
        "tags": ["Site"],
        "security": [{ "bearerAuth": [] }],
        "requestBody": {
          "required": true,
          "content": {
            "application/json": {
              "schema": {
                "type": "object",
                "properties": {
                  "name": { "type": "string" },
                  "url_address": { "type": "string" },
                  "user_id": { "type": "string" }
                },
                "required": ["name", "url_address", "user_id"]
              }
            }
          }
        },
        "responses": {
          "201": {
            "description": "Created",
            "content": {
              "application/json": {
                "schema": {
                  "type": "object",
                  "properties": {
                    "id": { "type": "string" },
                    "name": { "type": "string" },
                    "url_address": { "type": "string" },
                    "user_id": { "type": "string" }
                  }
                }
              }
            }
          },
          "400": {
            "description": "Bad Request",
            "content": {
              "application/json": {
                "schema": {
                  "type": "object",
                  "properties": {
                    "error": { "type": "string" }
                  }
                }
              }
            }
          },
          "401": {
            "description": "Unauthorized"
          },
          "404": {
            "description": "Not Found",
            "content": {
              "application/json": {
                "schema": {
                  "type": "object",
                  "properties": {
                    "error": { "type": "string" }
                  }
                }
              }
            }
          },
          "406": {
            "description": "Not Acceptable",
            "content": {
              "application/json": {
                "schema": {
                  "type": "object",
                  "properties": {
                    "error": { "type": "string" }
                  }
                }
              }
            }
          },
          "409": {
            "description": "Conflict",
            "content": {
              "application/json": {
                "schema": {
                  "type": "object",
                  "properties": {
                    "error": { "type": "string" }
                  }
                }
              }
            }
          },
          "500": {
            "description": "Internal Server Error",
            "content": {
              "application/json": {
                "schema": {
                  "type": "object",
                  "properties": {
                    "error": { "type": "string" }
                  }
                }
              }
            }
          }
        }
      },
      "get": {
        "summary": "Obter sites do usuário",
        "description": "Retorna a lista de sites de um usuário",
        "tags": ["Site"],
        "security": [{ "bearerAuth": [] }],
        "parameters": [
          {
            "name": "userId",
            "in": "query",
            "required": true,
            "schema": {
              "type": "string"
            },
            "description": "ID do usuário"
          }
        ],
        "responses": {
          "200": {
            "description": "OK",
            "content": {
              "application/json": {
                "schema": {
                  "type": "object",
                  "properties": {
                    "sites": {
                      "type": "array",
                      "items": {
                        "type": "object",
                        "properties": {
                          "id": { "type": "string" },
                          "name": { "type": "string" }
                        }
                      }
                    }
                  }
                }
              }
            }
          },
          "400": {
            "description": "Bad Request",
            "content": {
              "application/json": {
                "schema": {
                  "type": "object",
                  "properties": {
                    "error": { "type": "string" }
                  }
                }
              }
            }
          },
          "401": {
            "description": "Unauthorized"
          },
          "404": {
            "description": "Not Found",
            "content": {
              "application/json": {
                "schema": {
                  "type": "object",
                  "properties": {
                    "error": { "type": "string" }
                  }
                }
              }
            }
          },
          "406": {
            "description": "Not Acceptable",
            "content": {
              "application/json": {
                "schema": {
                  "type": "object",
                  "properties": {
                    "error": { "type": "string" }
                  }
                }
              }
            }
          },
          "500": {
            "description": "Internal Server Error",
            "content": {
              "application/json": {
                "schema": {
                  "type": "object",
                  "properties": {
                    "error": { "type": "string" }
                  }
                }
              }
            }
          }
        }
      }
    },
    "/site/{id}": {
      "put": {
        "summary": "Atualizar um site",
        "description": "Atualiza um site existente no sistema com base em seu ID",
        "tags": ["Site"],
        "security": [{ "bearerAuth": [] }],
        "parameters": [
          {
            "name": "id",
            "in": "path",
            "required": true,
            "schema": {
              "type": "string"
            },
            "description": "ID do site"
          }
        ],
        "requestBody": {
          "required": true,
          "content": {
            "application/json": {
              "schema": {
                "type": "object",
                "properties": {
                  "name": { "type": "string" },
                  "url_address": { "type": "string" }
                },
                "required": ["name", "url_address"]
              }
            }
          }
        },
        "responses": {
          "200": {
            "description": "OK",
            "content": {
              "application/json": {
                "schema": {
                  "type": "object",
                  "properties": {
                    "id": { "type": "string" },
                    "name": { "type": "string" },
                    "url_address": { "type": "string" },
                    "user_id": { "type": "string" }
                  }
                }
              }
            }
          },
          "400": {
            "description": "Bad Request",
            "content": {
              "application/json": {
                "schema": {
                  "type": "object",
                  "properties": {
                    "error": { "type": "string" }
                  }
                }
              }
            }
          },
          "401": {
            "description": "Unauthorized"
          },
          "404": {
            "description": "Not Found",
            "content": {
              "application/json": {
                "schema": {
                  "type": "object",
                  "properties": {
                    "error": { "type": "string" }
                  }
                }
              }
            }
          },
          "406": {
            "description": "Not Acceptable",
            "content": {
              "application/json": {
                "schema": {
                  "type": "object",
                  "properties": {
                    "error": { "type": "string" }
                  }
                }
              }
            }
          },
          "409": {
            "description": "Conflict",
            "content": {
              "application/json": {
                "schema": {
                  "type": "object",
                  "properties": {
                    "error": { "type": "string" }
                  }
                }
              }
            }
          },
          "500": {
            "description": "Internal Server Error",
            "content": {
              "application/json": {
                "schema": {
                  "type": "object",
                  "properties": {
                    "error": { "type": "string" }
                  }
                }
              }
            }
          }
        }
      },
      "delete": {
        "summary": "Deletar um site",
        "description": "Deleta um site existente no sistema com base em seu ID",
        "tags": ["Site"],
        "security": [{ "bearerAuth": [] }],
        "parameters": [
          {
            "name": "id",
            "in": "path",
            "required": true,
            "schema": {
              "type": "string"
            },
            "description": "ID do site"
          }
        ],
        "responses": {
          "204": {
            "description": "No Content"
          },
          "401": {
            "description": "Unauthorized"
          },
          "404": {
            "description": "Not Found",
            "content": {
              "application/json": {
                "schema": {
                  "type": "object",
                  "properties": {
                    "error": { "type": "string" }
                  }
                }
              }
            }
          },
          "406": {
            "description": "Not Acceptable",
            "content": {
              "application/json": {
                "schema": {
                  "type": "object",
                  "properties": {
                    "error": { "type": "string" }
                  }
                }
              }
            }
          },
          "500": {
            "description": "Internal Server Error",
            "content": {
              "application/json": {
                "schema": {
                  "type": "object",
                  "properties": {
                    "error": { "type": "string" }
                  }
                }
              }
            }
          }
        }
      }
    },
    "/strategy": {
      "post": {
        "summary": "Criar uma nova estratégia",
        "description": "Cria uma nova estratégia no sistema",
        "tags": ["Strategy"],
        "security": [{ "bearerAuth": [] }],
        "requestBody": {
          "required": true,
          "content": {
            "application/json": {
              "schema": {
                "type": "object",
                "properties": {
                  "name": { "type": "string" },
                  "commodity_id": { "type": "string" },
                  "user_id": { "type": "string" },
                  "sites_ids": {
                    "type": "array",
                    "items": { "type": "string" }
                  },
                  "tokens_ids": {
                    "type": "array",
                    "items": { "type": "string" }
                  }
                },
                "required": ["name", "commodity_id", "user_id", "sites_ids", "tokens_ids"]
              }
            }
          }
        },
        "responses": {
          "201": {
            "description": "Created",
            "content": {
              "application/json": {
                "schema": {
                  "type": "object",
                  "properties": {
                    "id": { "type": "string" },
                    "name": { "type": "string" },
                    "commodity_id": { "type": "string" }
                  }
                }
              }
            }
          },
          "400": {
            "description": "Bad Request",
            "content": {
              "application/json": {
                "schema": {
                  "type": "object",
                  "properties": {
                    "error": { "type": "string" }
                  }
                }
              }
            }
          },
          "401": {
            "description": "Unauthorized"
          },
          "404": {
            "description": "Not Found",
            "content": {
              "application/json": {
                "schema": {
                  "type": "object",
                  "properties": {
                    "error": { "type": "string" }
                  }
                }
              }
            }
          },
          "406": {
            "description": "Not Acceptable",
            "content": {
              "application/json": {
                "schema": {
                  "type": "object",
                  "properties": {
                    "error": { "type": "string" }
                  }
                }
              }
            }
          },
          "409": {
            "description": "Conflict",
            "content": {
              "application/json": {
                "schema": {
                  "type": "object",
                  "properties": {
                    "error": { "type": "string" }
                  }
                }
              }
            }
          },
          "500": {
            "description": "Internal Server Error",
            "content": {
              "application/json": {
                "schema": {
                  "type": "object",
                  "properties": {
                    "error": { "type": "string" }
                  }
                }
              }
            }
          }
        }
      },
      "get": {
        "summary": "Obter estratégias do usuário",
        "description": "Retorna a lista de estratégias de um usuário",
        "tags": ["Strategy"],
        "security": [{ "bearerAuth": [] }],
        "parameters": [
          {
            "name": "userId",
            "in": "query",
            "required": true,
            "schema": {
              "type": "string"
            },
            "description": "ID do usuário"
          }
        ],
        "responses": {
          "200": {
            "description": "OK",
            "content": {
              "application/json": {
                "schema": {
                  "type": "object",
                  "properties": {
                    "strategies": {
                      "type": "array",
                      "items": {
                        "type": "object",
                        "properties": {
                          "id": { "type": "string" },
                          "name": { "type": "string" },
                          "commodity": { "type": "string" }
                        }
                      }
                    }
                  }
                }
              }
            }
          },
          "400": {
            "description": "Bad Request",
            "content": {
              "application/json": {
                "schema": {
                  "type": "object",
                  "properties": {
                    "error": { "type": "string" }
                  }
                }
              }
            }
          },
          "401": {
            "description": "Unauthorized"
          },
          "404": {
            "description": "Not Found",
            "content": {
              "application/json": {
                "schema": {
                  "type": "object",
                  "properties": {
                    "error": { "type": "string" }
                  }
                }
              }
            }
          },
          "406": {
            "description": "Not Acceptable",
            "content": {
              "application/json": {
                "schema": {
                  "type": "object",
                  "properties": {
                    "error": { "type": "string" }
                  }
                }
              }
            }
          },
          "500": {
            "description": "Internal Server Error",
            "content": {
              "application/json": {
                "schema": {
                  "type": "object",
                  "properties": {
                    "error": { "type": "string" }
                  }
                }
              }
            }
          }
        }
      }
    },
    "/strategy/{id}": {
      "put": {
        "summary": "Atualizar uma estratégia",
        "description": "Atualiza uma estratégia existente no sistema com base em seu ID",
        "tags": ["Strategy"],
        "security": [{ "bearerAuth": [] }],
        "parameters": [
          {
            "name": "id",
            "in": "path",
            "required": true,
            "schema": {
              "type": "string"
            },
            "description": "ID da estratégia"
          }
        ],
        "requestBody": {
          "required": true,
          "content": {
            "application/json": {
              "schema": {
                "type": "object",
                "properties": {
                  "name": { "type": "string" },
                  "commodity_id": { "type": "string" },
                  "sites_ids": {
                    "type": "array",
                    "items": { "type": "string" }
                  },
                  "tokens_ids": {
                    "type": "array",
                    "items": { "type": "string" }
                  }
                },
                "required": ["name", "commodity_id", "sites_ids", "tokens_ids"]
              }
            }
          }
        },
        "responses": {
          "200": {
            "description": "OK",
            "content": {
              "application/json": {
                "schema": {
                  "type": "object",
                  "properties": {
                    "id": { "type": "string" },
                    "name": { "type": "string" },
                    "commodity_id": { "type": "string" }
                  }
                }
              }
            }
          },
          "400": {
            "description": "Bad Request",
            "content": {
              "application/json": {
                "schema": {
                  "type": "object",
                  "properties": {
                    "error": { "type": "string" }
                  }
                }
              }
            }
          },
          "401": {
            "description": "Unauthorized"
          },
          "404": {
            "description": "Not Found",
            "content": {
              "application/json": {
                "schema": {
                  "type": "object",
                  "properties": {
                    "error": { "type": "string" }
                  }
                }
              }
            }
          },
          "406": {
            "description": "Not Acceptable",
            "content": {
              "application/json": {
                "schema": {
                  "type": "object",
                  "properties": {
                    "error": { "type": "string" }
                  }
                }
              }
            }
          },
          "409": {
            "description": "Conflict",
            "content": {
              "application/json": {
                "schema": {
                  "type": "object",
                  "properties": {
                    "error": { "type": "string" }
                  }
                }
              }
            }
          },
          "500": {
            "description": "Internal Server Error",
            "content": {
              "application/json": {
                "schema": {
                  "type": "object",
                  "properties": {
                    "error": { "type": "string" }
                  }
                }
              }
            }
          }
        }
      }
    },
    "/token": {
      "post": {
        "summary": "Criar um novo token",
        "description": "Cria um novo token no sistema",
        "tags": ["Token"],
        "security": [{ "bearerAuth": [] }],
        "requestBody": {
          "required": true,
          "content": {
            "application/json": {
              "schema": {
                "type": "object",
                "properties": {
                  "token": { "type": "string" },
                  "user_id": { "type": "string" }
                },
                "required": ["token", "user_id"]
              }
            }
          }
        },
        "responses": {
          "201": {
            "description": "Created",
            "content": {
              "application/json": {
                "schema": {
                  "type": "object",
                  "properties": {
                    "id": { "type": "string" },
                    "token": { "type": "string" },
                    "user_id": { "type": "string" }
                  }
                }
              }
            }
          },
          "400": {
            "description": "Bad Request",
            "content": {
              "application/json": {
                "schema": {
                  "type": "object",
                  "properties": {
                    "error": { "type": "string" }
                  }
                }
              }
            }
          },
          "401": {
            "description": "Unauthorized"
          },
          "404": {
            "description": "Not Found",
            "content": {
              "application/json": {
                "schema": {
                  "type": "object",
                  "properties": {
                    "error": { "type": "string" }
                  }
                }
              }
            }
          },
          "406": {
            "description": "Not Acceptable",
            "content": {
              "application/json": {
                "schema": {
                  "type": "object",
                  "properties": {
                    "error": { "type": "string" }
                  }
                }
              }
            }
          },
          "409": {
            "description": "Conflict",
            "content": {
              "application/json": {
                "schema": {
                  "type": "object",
                  "properties": {
                    "error": { "type": "string" }
                  }
                }
              }
            }
          },
          "500": {
            "description": "Internal Server Error",
            "content": {
              "application/json": {
                "schema": {
                  "type": "object",
                  "properties": {
                    "error": { "type": "string" }
                  }
                }
              }
            }
          }
        }
      },
      "get": {
        "summary": "Obter tokens do usuário",
        "description": "Retorna a lista de tokens de um usuário",
        "tags": ["Token"],
        "security": [{ "bearerAuth": [] }],
        "parameters": [
          {
            "name": "userId",
            "in": "query",
            "required": true,
            "schema": {
              "type": "string"
            },
            "description": "ID do usuário"
          }
        ],
        "responses": {
          "200": {
            "description": "OK",
            "content": {
              "application/json": {
                "schema": {
                  "type": "object",
                  "properties": {
                    "tokens": {
                      "type": "array",
                      "items": {
                        "type": "object",
                        "properties": {
                          "id": { "type": "string" },
                          "token": { "type": "string" }
                        }
                      }
                    }
                  }
                }
              }
            }
          },
          "400": {
            "description": "Bad Request",
            "content": {
              "application/json": {
                "schema": {
                  "type": "object",
                  "properties": {
                    "error": { "type": "string" }
                  }
                }
              }
            }
          },
          "401": {
            "description": "Unauthorized"
          },
          "404": {
            "description": "Not Found",
            "content": {
              "application/json": {
                "schema": {
                  "type": "object",
                  "properties": {
                    "error": { "type": "string" }
                  }
                }
              }
            }
          },
          "406": {
            "description": "Not Acceptable",
            "content": {
              "application/json": {
                "schema": {
                  "type": "object",
                  "properties": {
                    "error": { "type": "string" }
                  }
                }
              }
            }
          },
          "500": {
            "description": "Internal Server Error",
            "content": {
              "application/json": {
                "schema": {
                  "type": "object",
                  "properties": {
                    "error": { "type": "string" }
                  }
                }
              }
            }
          }
        }
      }
    },
    "/token/{id}": {
      "put": {
        "summary": "Atualizar um token",
        "description": "Atualiza um token existente no sistema com base em seu ID",
        "tags": ["Token"],
        "security": [{ "bearerAuth": [] }],
        "parameters": [
          {
            "name": "id",
            "in": "path",
            "required": true,
            "schema": {
              "type": "string"
            },
            "description": "ID do token"
          }
        ],
        "requestBody": {
          "required": true,
          "content": {
            "application/json": {
              "schema": {
                "type": "object",
                "properties": {
                  "new_token": { "type": "string" }
                },
                "required": ["new_token"]
              }
            }
          }
        },
        "responses": {
          "200": {
            "description": "OK",
            "content": {
              "application/json": {
                "schema": {
                  "type": "object",
                  "properties": {
                    "id": { "type": "string" },
                    "token": { "type": "string" },
                    "user_id": { "type": "string" }
                  }
                }
              }
            }
          },
          "400": {
            "description": "Bad Request",
            "content": {
              "application/json": {
                "schema": {
                  "type": "object",
                  "properties": {
                    "error": { "type": "string" }
                  }
                }
              }
            }
          },
          "401": {
            "description": "Unauthorized"
          },
          "404": {
            "description": "Not Found",
            "content": {
              "application/json": {
                "schema": {
                  "type": "object",
                  "properties": {
                    "error": { "type": "string" }
                  }
                }
              }
            }
          },
          "406": {
            "description": "Not Acceptable",
            "content": {
              "application/json": {
                "schema": {
                  "type": "object",
                  "properties": {
                    "error": { "type": "string" }
                  }
                }
              }
            }
          },
          "409": {
            "description": "Conflict",
            "content": {
              "application/json": {
                "schema": {
                  "type": "object",
                  "properties": {
                    "error": { "type": "string" }
                  }
                }
              }
            }
          },
          "500": {
            "description": "Internal Server Error",
            "content": {
              "application/json": {
                "schema": {
                  "type": "object",
                  "properties": {
                    "error": { "type": "string" }
                  }
                }
              }
            }
          }
        }
      },
      "delete": {
        "summary": "Deletar um token",
        "description": "Deleta um token existente no sistema com base em seu ID",
        "tags": ["Token"],
        "security": [{ "bearerAuth": [] }],
        "parameters": [
          {
            "name": "id",
            "in": "path",
            "required": true,
            "schema": {
              "type": "string"
            },
            "description": "ID do token"
          }
        ],
        "responses": {
          "204": {
            "description": "No Content"
          },
          "401": {
            "description": "Unauthorized"
          },
          "404": {
            "description": "Not Found",
            "content": {
              "application/json": {
                "schema": {
                  "type": "object",
                  "properties": {
                    "error": { "type": "string" }
                  }
                }
              }
            }
          },
          "406": {
            "description": "Not Acceptable",
            "content": {
              "application/json": {
                "schema": {
                  "type": "object",
                  "properties": {
                    "error": { "type": "string" }
                  }
                }
              }
            }
          },
          "500": {
            "description": "Internal Server Error",
            "content": {
              "application/json": {
                "schema": {
                  "type": "object",
                  "properties": {
                    "error": { "type": "string" }
                  }
                }
              }
            }
          }
        }
      }
    },
    "/user": {
      "post": {
        "summary": "Criar um novo usuário",
        "description": "Cria um novo usuário no sistema",
        "tags": ["User"],
        "requestBody": {
          "required": true,
          "content": {
            "application/json": {
              "schema": {
              "type": "object",
              "properties": {
                "first_name": { "type": "string" },
                "last_name": { "type": "string" },
                "email": { "type": "string" },
                "phone": { "type": "string" },
                "password": { "type": "string" }
              },
              "required": ["first_name", "last_name", "email", "phone", "password"]
              }
            }
          }
        },
        "responses": {
          "201": {
            "description": "Created",
            "content": {
                "application/json": {
                "schema": {
                  "type": "object",
                  "properties": {
                  "id": { "type": "string" },
                  "first_name": { "type": "string" },
                  "last_name": { "type": "string" },
                  "email": { "type": "string" },
                  "phone": { "type": "string" }
                  }
                }
              }
            }
          },
          "401": {
            "description": "Unauthorized"
          },
          "400": {
            "description": "Bad Request",
            "content": {
              "application/json": {
                "schema": {
                  "type": "object",
                  "properties": {
                    "error": {
                      "type": "string"
                    }
                  }
                }
              }
            }
          },
          "409": {
            "description": "Conflict",
            "content": {
              "application/json": {
                "schema": {
                  "type": "object",
                  "properties": {
                    "error": {
                      "type": "string"
                    }
                  }
                }
              }
            }
          }
        }
      }
    }
  },
  "components": {
    "securitySchemes": {
      "bearerAuth": {
        "type": "http",
        "scheme": "bearer",
        "bearerFormat": "JWT"
      }
    }
  }
}